[
  {
    "type": "object",
    "usage": "always",
    "schema": {
      "archived": [
        {
          "type": "bool",
          "usage": "always",
          "schema": {
            "true": 331048,
            "false": 12
          }
        }
      ],
      "author": [
        {
          "type": "string",
          "usage": "always",
          "schema": {
            "min_length": 0,
            "max_length": 20,
            "avr_length": 9.05
          }
        }
      ],
      "author_flair_background_color": [
        {
          "type": "null",
          "usage": 0.79,
          "schema": null
        },
        {
          "type": "string",
          "usage": 0.21,
          "schema": {
            "min_length": 0,
            "max_length": 0,
            "avr_length": 0.0,
            "values": [
              {
                "value": "",
                "usage": "always"
              }
            ]
          }
        }
      ],
      "author_flair_css_class": [
        {
          "type": "null",
          "usage": 1.0,
          "schema": null
        },
        {
          "type": "string",
          "usage": 0.0,
          "schema": {
            "min_length": 0,
            "max_length": 27,
            "avr_length": 7.0
          }
        }
      ],
      "author_flair_text": [
        {
          "type": "null",
          "usage": 1.0,
          "schema": null
        },
        {
          "type": "string",
          "usage": 0.0,
          "schema": {
            "min_length": 0,
            "max_length": 60,
            "avr_length": 11.78
          }
        }
      ],
      "author_flair_text_color": [
        {
          "type": "null",
          "usage": 0.79,
          "schema": null
        },
        {
          "type": "string",
          "usage": 0.21,
          "schema": {
            "min_length": 0,
            "max_length": 4,
            "avr_length": 4.0,
            "values": [
              {
                "value": "dark",
                "usage": "always"
              }
            ]
          }
        }
      ],
      "brand_safe": [
        {
          "type": "bool",
          "usage": "always",
          "schema": {
            "true": 278537,
            "false": 52523
          }
        }
      ],
      "can_gild": [
        {
          "type": "bool",
          "usage": "always",
          "schema": {
            "true": 260369,
            "false": 70691
          }
        }
      ],
      "contest_mode": [
        {
          "type": "bool",
          "usage": "always",
          "schema": {
            "true": 0,
            "false": 331060
          }
        }
      ],
      "created_utc": [
        {
          "type": "int",
          "usage": "always",
          "schema": {
            "min_value": 0,
            "max_value": 1233446396,
            "avr_value": 1232168587.72
          }
        }
      ],
      "distinguished": [
        {
          "type": "null",
          "usage": 1.0,
          "schema": null
        },
        {
          "type": "string",
          "usage": 0.0,
          "schema": {
            "min_length": 0,
            "max_length": 9,
            "avr_length": 9.0,
            "values": [
              {
                "value": "moderator",
                "usage": "always"
              }
            ]
          }
        }
      ],
      "domain": [
        {
          "type": "string",
          "usage": "always",
          "schema": {
            "min_length": 0,
            "max_length": 174,
            "avr_length": 16.43
          }
        }
      ],
      "edited": [
        {
          "type": "bool",
          "usage": 1.0,
          "schema": {
            "true": 0,
            "false": 331058
          }
        },
        {
          "type": "float",
          "usage": 0.0,
          "schema": {
            "min_value": 0,
            "max_value": 1475176610.0,
            "avr_value": 1354120622.0
          }
        }
      ],
      "gilded": [
        {
          "type": "int",
          "usage": "always",
          "schema": {
            "min_value": 0,
            "max_value": 0,
            "avr_value": 0.0
          }
        }
      ],
      "hidden": [
        {
          "type": "bool",
          "usage": "always",
          "schema": {
            "true": 0,
            "false": 331060
          }
        }
      ],
      "hide_score": [
        {
          "type": "bool",
          "usage": "always",
          "schema": {
            "true": 5,
            "false": 331055
          }
        }
      ],
      "id": [
        {
          "type": "string",
          "usage": "always",
          "schema": {
            "min_length": 0,
            "max_length": 5,
            "avr_length": 5.0
          }
        }
      ],
      "is_crosspostable": [
        {
          "type": "bool",
          "usage": "always",
          "schema": {
            "true": 144504,
            "false": 186556
          }
        }
      ],
      "is_reddit_media_domain": [
        {
          "type": "bool",
          "usage": "always",
          "schema": {
            "true": 0,
            "false": 331060
          }
        }
      ],
      "is_self": [
        {
          "type": "bool",
          "usage": "always",
          "schema": {
            "true": 11462,
            "false": 319598
          }
        }
      ],
      "is_video": [
        {
          "type": "bool",
          "usage": "always",
          "schema": {
            "true": 0,
            "false": 331060
          }
        }
      ],
      "link_flair_css_class": [
        {
          "type": "null",
          "usage": 1.0,
          "schema": null
        },
        {
          "type": "string",
          "usage": 0.0,
          "schema": {
            "min_length": 0,
            "max_length": 7,
            "avr_length": 3.75,
            "values": [
              {
                "value": "article",
                "usage": 0.12
              },
              {
                "value": "legal",
                "usage": 0.12
              },
              {
                "value": "history",
                "usage": 0.12
              },
              {
                "value": "",
                "usage": 0.38
              },
              {
                "value": "brown",
                "usage": 0.12
              },
              {
                "value": "normal",
                "usage": 0.12
              }
            ]
          }
        }
      ],
      "link_flair_richtext": [
        {
          "type": "array",
          "usage": "always",
          "schema": {
            "min_length": 0,
            "max_length": 1,
            "avr_length": 0.0,
            "schema": [
              {
                "type": "object",
                "usage": "always",
                "schema": {
                  "e": [
                    {
                      "type": "string",
                      "usage": "always",
                      "schema": {
                        "min_length": 0,
                        "max_length": 4,
                        "avr_length": 4.0,
                        "values": [
                          {
                            "value": "text",
                            "usage": "always"
                          }
                        ]
                      }
                    }
                  ],
                  "t": [
                    {
                      "type": "string",
                      "usage": "always",
                      "schema": {
                        "min_length": 0,
                        "max_length": 14,
                        "avr_length": 7.22,
                        "values": [
                          {
                            "value": "Article",
                            "usage": 0.11
                          },
                          {
                            "value": "Legal",
                            "usage": 0.11
                          },
                          {
                            "value": "HISTORY",
                            "usage": 0.11
                          },
                          {
                            "value": "[suicidewatch]",
                            "usage": 0.11
                          },
                          {
                            "value": "Video",
                            "usage": 0.33
                          },
                          {
                            "value": "Politics",
                            "usage": 0.11
                          },
                          {
                            "value": "No videos",
                            "usage": 0.11
                          }
                        ]
                      }
                    }
                  ]
                }
              }
            ]
          }
        }
      ],
      "link_flair_text": [
        {
          "type": "null",
          "usage": 1.0,
          "schema": null
        },
        {
          "type": "string",
          "usage": 0.0,
          "schema": {
            "min_length": 0,
            "max_length": 14,
            "avr_length": 7.22,
            "values": [
              {
                "value": "Article",
                "usage": 0.11
              },
              {
                "value": "Legal",
                "usage": 0.11
              },
              {
                "value": "HISTORY",
                "usage": 0.11
              },
              {
                "value": "[suicidewatch]",
                "usage": 0.11
              },
              {
                "value": "Video",
                "usage": 0.33
              },
              {
                "value": "Politics",
                "usage": 0.11
              },
              {
                "value": "No videos",
                "usage": 0.11
              }
            ]
          }
        }
      ],
      "link_flair_text_color": [
        {
          "type": "string",
          "usage": "always",
          "schema": {
            "min_length": 0,
            "max_length": 4,
            "avr_length": 4.0,
            "values": [
              {
                "value": "dark",
                "usage": "always"
              }
            ]
          }
        }
      ],
      "link_flair_type": [
        {
          "type": "string",
          "usage": "always",
          "schema": {
            "min_length": 0,
            "max_length": 8,
            "avr_length": 4.0,
            "values": [
              {
                "value": "text",
                "usage": 1.0
              },
              {
                "value": "richtext",
                "usage": 0.0
              }
            ]
          }
        }
      ],
      "locked": [
        {
          "type": "bool",
          "usage": "always",
          "schema": {
            "true": 0,
            "false": 331060
          }
        }
      ],
      "media": [
        {
          "type": "null",
          "usage": 1.0,
          "schema": null
        },
        {
          "type": "object",
          "usage": 0.0,
          "schema": {
            "oembed": [
              {
                "type": "object",
                "usage": "always",
                "schema": {
                  "height": [
                    {
                      "type": "int",
                      "usage": "always",
                      "schema": {
                        "min_value": 0,
                        "max_value": 800,
                        "avr_value": 382.18
                      }
                    }
                  ],
                  "html": [
                    {
                      "type": "string",
                      "usage": "always",
                      "schema": {
                        "min_length": 0,
                        "max_length": 561,
                        "avr_length": 305.55
                      }
                    }
                  ],
                  "provider_name": [
                    {
                      "type": "string",
                      "usage": "always",
                      "schema": {
                        "min_length": 0,
                        "max_length": 7,
                        "avr_length": 6.91,
                        "values": [
                          {
                            "value": "YouTube",
                            "usage": 0.91
                          },
                          {
                            "value": "Scribd",
                            "usage": 0.09
                          }
                        ]
                      }
                    }
                  ],
                  "provider_url": [
                    {
                      "type": "string",
                      "usage": "always",
                      "schema": {
                        "min_length": 0,
                        "max_length": 24,
                        "avr_length": 23.36,
                        "values": [
                          {
                            "value": "http://youtube.com",
                            "usage": 0.09
                          },
                          {
                            "value": "https://www.youtube.com/",
                            "usage": 0.82
                          },
                          {
                            "value": "https://www.scribd.com/",
                            "usage": 0.09
                          }
                        ]
                      }
                    }
                  ],
                  "thumbnail_height": [
                    {
                      "type": "int",
                      "usage": "always",
                      "schema": {
                        "min_value": 0,
                        "max_value": 360,
                        "avr_value": 315.64
                      }
                    }
                  ],
                  "thumbnail_url": [
                    {
                      "type": "string",
                      "usage": "always",
                      "schema": {
                        "min_length": 0,
                        "max_length": 184,
                        "avr_length": 75.55
                      }
                    }
                  ],
                  "thumbnail_width": [
                    {
                      "type": "int",
                      "usage": "always",
                      "schema": {
                        "min_value": 0,
                        "max_value": 480,
                        "avr_value": 413.73
                      }
                    }
                  ],
                  "title": [
                    {
                      "type": "string",
                      "usage": "always",
                      "schema": {
                        "min_length": 0,
                        "max_length": 62,
                        "avr_length": 32.73
                      }
                    }
                  ],
                  "type": [
                    {
                      "type": "string",
                      "usage": "always",
                      "schema": {
                        "min_length": 0,
                        "max_length": 5,
                        "avr_length": 4.91,
                        "values": [
                          {
                            "value": "video",
                            "usage": 0.91
                          },
                          {
                            "value": "rich",
                            "usage": 0.09
                          }
                        ]
                      }
                    }
                  ],
                  "version": [
                    {
                      "type": "string",
                      "usage": "always",
                      "schema": {
                        "min_length": 0,
                        "max_length": 3,
                        "avr_length": 3.0,
                        "values": [
                          {
                            "value": "1.0",
                            "usage": "always"
                          }
                        ]
                      }
                    }
                  ],
                  "width": [
                    {
                      "type": "int",
                      "usage": "always",
                      "schema": {
                        "min_value": 0,
                        "max_value": 600,
                        "avr_value": 548.73
                      }
                    }
                  ],
                  "author_name": [
                    {
                      "type": "string",
                      "usage": "always",
                      "schema": {
                        "min_length": 0,
                        "max_length": 20,
                        "avr_length": 10.5,
                        "values": [
                          {
                            "value": "manchesterunitedpimp",
                            "usage": 0.1
                          },
                          {
                            "value": "Bright",
                            "usage": 0.1
                          },
                          {
                            "value": "RT",
                            "usage": 0.1
                          },
                          {
                            "value": "pirateonboard",
                            "usage": 0.1
                          },
                          {
                            "value": "Hagit Leibowitz",
                            "usage": 0.1
                          },
                          {
                            "value": "Machinima",
                            "usage": 0.1
                          },
                          {
                            "value": "britpod",
                            "usage": 0.1
                          },
                          {
                            "value": "The Young Turks",
                            "usage": 0.1
                          },
                          {
                            "value": "lulusparky",
                            "usage": 0.1
                          },
                          {
                            "value": "MASS LBP",
                            "usage": 0.1
                          }
                        ]
                      }
                    }
                  ],
                  "author_url": [
                    {
                      "type": "string",
                      "usage": "always",
                      "schema": {
                        "min_length": 0,
                        "max_length": 49,
                        "avr_length": 40.8
                      }
                    }
                  ],
                  "url": [
                    {
                      "type": "string",
                      "usage": "always",
                      "schema": {
                        "min_length": 0,
                        "max_length": 42,
                        "avr_length": 42.0
                      }
                    }
                  ],
                  "description": [
                    {
                      "type": "string",
                      "usage": "always",
                      "schema": {
                        "min_length": 0,
                        "max_length": 391,
                        "avr_length": 311.0
                      }
                    }
                  ],
                  "cache_age": [
                    {
                      "type": "int",
                      "usage": "always",
                      "schema": {
                        "min_value": 0,
                        "max_value": 604800,
                        "avr_value": 604800.0
                      }
                    }
                  ]
                }
              }
            ],
            "type": [
              {
                "type": "string",
                "usage": "always",
                "schema": {
                  "min_length": 0,
                  "max_length": 14,
                  "avr_length": 11.45,
                  "values": [
                    {
                      "value": "jp.youtube.com",
                      "usage": 0.09
                    },
                    {
                      "value": "youtube.com",
                      "usage": 0.73
                    },
                    {
                      "value": "uk.youtube.com",
                      "usage": 0.09
                    },
                    {
                      "value": "scribd.com",
                      "usage": 0.09
                    }
                  ]
                }
              }
            ]
          }
        }
      ],
      "media_embed": [
        {
          "type": "object",
          "usage": "always",
          "schema": {
            "content": [
              {
                "type": "string",
                "usage": "always",
                "schema": {
                  "min_length": 0,
                  "max_length": 561,
                  "avr_length": 305.55
                }
              }
            ],
            "height": [
              {
                "type": "int",
                "usage": "always",
                "schema": {
                  "min_value": 0,
                  "max_value": 800,
                  "avr_value": 382.18
                }
              }
            ],
            "media_domain_url": [
              {
                "type": "string",
                "usage": "always",
                "schema": {
                  "min_length": 0,
                  "max_length": 44,
                  "avr_length": 44.0
                }
              }
            ],
            "scrolling": [
              {
                "type": "bool",
                "usage": "always",
                "schema": {
                  "true": 0,
                  "false": 11
                }
              }
            ],
            "width": [
              {
                "type": "int",
                "usage": "always",
                "schema": {
                  "min_value": 0,
                  "max_value": 600,
                  "avr_value": 548.73
                }
              }
            ]
          }
        }
      ],
      "no_follow": [
        {
          "type": "bool",
          "usage": "always",
          "schema": {
            "true": 259599,
            "false": 71461
          }
        }
      ],
      "num_comments": [
        {
          "type": "int",
          "usage": "always",
          "schema": {
            "min_value": 0,
            "max_value": 22421,
            "avr_value": 2.95
          }
        }
      ],
      "num_crossposts": [
        {
          "type": "int",
          "usage": "always",
          "schema": {
            "min_value": 0,
            "max_value": 1,
            "avr_value": 0.0
          }
        }
      ],
      "over_18": [
        {
          "type": "bool",
          "usage": "always",
          "schema": {
            "true": 9065,
            "false": 321995
          }
        }
      ],
      "parent_whitelist_status": [
        {
          "type": "string",
          "usage": 0.91,
          "schema": {
            "min_length": 0,
            "max_length": 16,
            "avr_length": 7.6,
            "values": [
              {
                "value": "all_ads",
                "usage": 0.92
              },
              {
                "value": "promo_adult_nsfw",
                "usage": 0.03
              },
              {
                "value": "promo_specified",
                "usage": 0.04
              },
              {
                "value": "promo_adult",
                "usage": 0.0
              },
              {
                "value": "no_ads",
                "usage": 0.0
              },
              {
                "value": "promo_all",
                "usage": 0.0
              },
              {
                "value": "house_only",
                "usage": 0.0
              }
            ]
          }
        },
        {
          "type": "null",
          "usage": 0.09,
          "schema": null
        }
      ],
      "permalink": [
        {
          "type": "string",
          "usage": "always",
          "schema": {
            "min_length": 0,
            "max_length": 90,
            "avr_length": 65.6
          }
        }
      ],
      "retrieved_on": [
        {
          "type": "int",
          "usage": "always",
          "schema": {
            "min_value": 0,
            "max_value": 1522775525,
            "avr_value": 1522772876.03
          }
        }
      ],
      "rte_mode": [
        {
          "type": "string",
          "usage": "always",
          "schema": {
            "min_length": 0,
            "max_length": 8,
            "avr_length": 8.0,
            "values": [
              {
                "value": "markdown",
                "usage": "always"
              }
            ]
          }
        }
      ],
      "score": [
        {
          "type": "int",
          "usage": "always",
          "schema": {
            "min_value": 0,
            "max_value": 4745,
            "avr_value": 6.42
          }
        }
      ],
      "secure_media": [
        {
          "type": "null",
          "usage": 1.0,
          "schema": null
        },
        {
          "type": "object",
          "usage": 0.0,
          "schema": {
            "oembed": [
              {
                "type": "object",
                "usage": "always",
                "schema": {
                  "height": [
                    {
                      "type": "int",
                      "usage": "always",
                      "schema": {
                        "min_value": 0,
                        "max_value": 800,
                        "avr_value": 382.18
                      }
                    }
                  ],
                  "html": [
                    {
                      "type": "string",
                      "usage": "always",
                      "schema": {
                        "min_length": 0,
                        "max_length": 561,
                        "avr_length": 305.55
                      }
                    }
                  ],
                  "provider_name": [
                    {
                      "type": "string",
                      "usage": "always",
                      "schema": {
                        "min_length": 0,
                        "max_length": 7,
                        "avr_length": 6.91,
                        "values": [
                          {
                            "value": "YouTube",
                            "usage": 0.91
                          },
                          {
                            "value": "Scribd",
                            "usage": 0.09
                          }
                        ]
                      }
                    }
                  ],
                  "provider_url": [
                    {
                      "type": "string",
                      "usage": "always",
                      "schema": {
                        "min_length": 0,
                        "max_length": 24,
                        "avr_length": 23.36,
                        "values": [
                          {
                            "value": "http://youtube.com",
                            "usage": 0.09
                          },
                          {
                            "value": "https://www.youtube.com/",
                            "usage": 0.82
                          },
                          {
                            "value": "https://www.scribd.com/",
                            "usage": 0.09
                          }
                        ]
                      }
                    }
                  ],
                  "thumbnail_height": [
                    {
                      "type": "int",
                      "usage": "always",
                      "schema": {
                        "min_value": 0,
                        "max_value": 360,
                        "avr_value": 315.64
                      }
                    }
                  ],
                  "thumbnail_url": [
                    {
                      "type": "string",
                      "usage": "always",
                      "schema": {
                        "min_length": 0,
                        "max_length": 184,
                        "avr_length": 75.55
                      }
                    }
                  ],
                  "thumbnail_width": [
                    {
                      "type": "int",
                      "usage": "always",
                      "schema": {
                        "min_value": 0,
                        "max_value": 480,
                        "avr_value": 413.73
                      }
                    }
                  ],
                  "title": [
                    {
                      "type": "string",
                      "usage": "always",
                      "schema": {
                        "min_length": 0,
                        "max_length": 62,
                        "avr_length": 32.73
                      }
                    }
                  ],
                  "type": [
                    {
                      "type": "string",
                      "usage": "always",
                      "schema": {
                        "min_length": 0,
                        "max_length": 5,
                        "avr_length": 4.91,
                        "values": [
                          {
                            "value": "video",
                            "usage": 0.91
                          },
                          {
                            "value": "rich",
                            "usage": 0.09
                          }
                        ]
                      }
                    }
                  ],
                  "version": [
                    {
                      "type": "string",
                      "usage": "always",
                      "schema": {
                        "min_length": 0,
                        "max_length": 3,
                        "avr_length": 3.0,
                        "values": [
                          {
                            "value": "1.0",
                            "usage": "always"
                          }
                        ]
                      }
                    }
                  ],
                  "width": [
                    {
                      "type": "int",
                      "usage": "always",
                      "schema": {
                        "min_value": 0,
                        "max_value": 600,
                        "avr_value": 548.73
                      }
                    }
                  ],
                  "author_name": [
                    {
                      "type": "string",
                      "usage": "always",
                      "schema": {
                        "min_length": 0,
                        "max_length": 20,
                        "avr_length": 10.5,
                        "values": [
                          {
                            "value": "manchesterunitedpimp",
                            "usage": 0.1
                          },
                          {
                            "value": "Bright",
                            "usage": 0.1
                          },
                          {
                            "value": "RT",
                            "usage": 0.1
                          },
                          {
                            "value": "pirateonboard",
                            "usage": 0.1
                          },
                          {
                            "value": "Hagit Leibowitz",
                            "usage": 0.1
                          },
                          {
                            "value": "Machinima",
                            "usage": 0.1
                          },
                          {
                            "value": "britpod",
                            "usage": 0.1
                          },
                          {
                            "value": "The Young Turks",
                            "usage": 0.1
                          },
                          {
                            "value": "lulusparky",
                            "usage": 0.1
                          },
                          {
                            "value": "MASS LBP",
                            "usage": 0.1
                          }
                        ]
                      }
                    }
                  ],
                  "author_url": [
                    {
                      "type": "string",
                      "usage": "always",
                      "schema": {
                        "min_length": 0,
                        "max_length": 49,
                        "avr_length": 40.8
                      }
                    }
                  ],
                  "url": [
                    {
                      "type": "string",
                      "usage": "always",
                      "schema": {
                        "min_length": 0,
                        "max_length": 42,
                        "avr_length": 42.0
                      }
                    }
                  ],
                  "description": [
                    {
                      "type": "string",
                      "usage": "always",
                      "schema": {
                        "min_length": 0,
                        "max_length": 391,
                        "avr_length": 311.0
                      }
                    }
                  ],
                  "cache_age": [
                    {
                      "type": "int",
                      "usage": "always",
                      "schema": {
                        "min_value": 0,
                        "max_value": 604800,
                        "avr_value": 604800.0
                      }
                    }
                  ]
                }
              }
            ],
            "type": [
              {
                "type": "string",
                "usage": "always",
                "schema": {
                  "min_length": 0,
                  "max_length": 14,
                  "avr_length": 11.45,
                  "values": [
                    {
                      "value": "jp.youtube.com",
                      "usage": 0.09
                    },
                    {
                      "value": "youtube.com",
                      "usage": 0.73
                    },
                    {
                      "value": "uk.youtube.com",
                      "usage": 0.09
                    },
                    {
                      "value": "scribd.com",
                      "usage": 0.09
                    }
                  ]
                }
              }
            ]
          }
        }
      ],
      "secure_media_embed": [
        {
          "type": "object",
          "usage": "always",
          "schema": {
            "content": [
              {
                "type": "string",
                "usage": "always",
                "schema": {
                  "min_length": 0,
                  "max_length": 561,
                  "avr_length": 305.55
                }
              }
            ],
            "height": [
              {
                "type": "int",
                "usage": "always",
                "schema": {
                  "min_value": 0,
                  "max_value": 800,
                  "avr_value": 382.18
                }
              }
            ],
            "media_domain_url": [
              {
                "type": "string",
                "usage": "always",
                "schema": {
                  "min_length": 0,
                  "max_length": 44,
                  "avr_length": 44.0
                }
              }
            ],
            "scrolling": [
              {
                "type": "bool",
                "usage": "always",
                "schema": {
                  "true": 0,
                  "false": 11
                }
              }
            ],
            "width": [
              {
                "type": "int",
                "usage": "always",
                "schema": {
                  "min_value": 0,
                  "max_value": 600,
                  "avr_value": 548.73
                }
              }
            ]
          }
        }
      ],
      "selftext": [
        {
          "type": "string",
          "usage": "always",
          "schema": {
            "min_length": 0,
            "max_length": 9,
            "avr_length": 1.37,
            "values": [
              {
                "value": "[deleted]",
                "usage": 0.15
              },
              {
                "value": "",
                "usage": 0.85
              },
              {
                "value": "[removed]",
                "usage": 0.0
              }
            ]
          }
        }
      ],
      "send_replies": [
        {
          "type": "bool",
          "usage": "always",
          "schema": {
            "true": 331060,
            "false": 0
          }
        }
      ],
      "spoiler": [
        {
          "type": "bool",
          "usage": "always",
          "schema": {
            "true": 1,
            "false": 331059
          }
        }
      ],
      "stickied": [
        {
          "type": "bool",
          "usage": "always",
          "schema": {
            "true": 0,
            "false": 331060
          }
        }
      ],
      "subreddit": [
        {
          "type": "string",
          "usage": "always",
          "schema": {
            "min_length": 0,
            "max_length": 20,
            "avr_length": 8.39
          }
        }
      ],
      "subreddit_id": [
        {
          "type": "string",
          "usage": "always",
          "schema": {
            "min_length": 0,
            "max_length": 8,
            "avr_length": 6.22
          }
        }
      ],
      "subreddit_name_prefixed": [
        {
          "type": "string",
          "usage": "always",
          "schema": {
            "min_length": 0,
            "max_length": 22,
            "avr_length": 10.39
          }
        }
      ],
      "subreddit_type": [
        {
          "type": "string",
          "usage": "always",
          "schema": {
            "min_length": 0,
            "max_length": 10,
            "avr_length": 6.9,
            "values": [
              {
                "value": "public",
                "usage": 0.56
              },
              {
                "value": "archived",
                "usage": 0.43
              },
              {
                "value": "restricted",
                "usage": 0.01
              }
            ]
          }
        }
      ],
      "suggested_sort": [
        {
          "type": "null",
          "usage": 0.98,
          "schema": null
        },
        {
          "type": "string",
          "usage": 0.02,
          "schema": {
            "min_length": 0,
            "max_length": 10,
            "avr_length": 9.23,
            "values": [
              {
                "value": "confidence",
                "usage": 0.89
              },
              {
                "value": "top",
                "usage": 0.03
              },
              {
                "value": "new",
                "usage": 0.08
              }
            ]
          }
        }
      ],
      "thumbnail": [
        {
          "type": "string",
          "usage": "always",
          "schema": {
            "min_length": 0,
            "max_length": 80,
            "avr_length": 4.7
          }
        }
      ],
      "title": [
        {
          "type": "string",
          "usage": "always",
          "schema": {
            "min_length": 0,
            "max_length": 309,
            "avr_length": 52.09
          }
        }
      ],
      "url": [
        {
          "type": "string",
          "usage": "always",
          "schema": {
            "min_length": 0,
            "max_length": 2996,
            "avr_length": 70.06
          }
        }
      ],
      "whitelist_status": [
        {
          "type": "string",
          "usage": 0.91,
          "schema": {
            "min_length": 0,
            "max_length": 16,
            "avr_length": 7.63,
            "values": [
              {
                "value": "all_ads",
                "usage": 0.92
              },
              {
                "value": "promo_adult_nsfw",
                "usage": 0.03
              },
              {
                "value": "promo_specified",
                "usage": 0.04
              },
              {
                "value": "promo_adult",
                "usage": 0.0
              },
              {
                "value": "no_ads",
                "usage": 0.0
              },
              {
                "value": "promo_all",
                "usage": 0.0
              },
              {
                "value": "house_only",
                "usage": 0.0
              }
            ]
          }
        },
        {
          "type": "null",
          "usage": 0.09,
          "schema": null
        }
      ],
      "author_flair_richtext": [
        {
          "type": "array",
          "usage": "always",
          "schema": {
            "min_length": 0,
            "max_length": 1,
            "avr_length": 0.01,
            "schema": [
              {
                "type": "object",
                "usage": "always",
                "schema": {
                  "e": [
                    {
                      "type": "string",
                      "usage": "always",
                      "schema": {
                        "min_length": 0,
                        "max_length": 4,
                        "avr_length": 4.0,
                        "values": [
                          {
                            "value": "text",
                            "usage": "always"
                          }
                        ]
                      }
                    }
                  ],
                  "t": [
                    {
                      "type": "string",
                      "usage": "always",
                      "schema": {
                        "min_length": 0,
                        "max_length": 60,
                        "avr_length": 12.47
                      }
                    }
                  ]
                }
              }
            ]
          }
        }
      ],
      "author_flair_type": [
        {
          "type": "string",
          "usage": "always",
          "schema": {
            "min_length": 0,
            "max_length": 8,
            "avr_length": 4.02,
            "values": [
              {
                "value": "text",
                "usage": 0.99
              },
              {
                "value": "richtext",
                "usage": 0.01
              }
            ]
          }
        }
      ],
      "thumbnail_height": [
        {
          "type": "null",
          "usage": 1.0,
          "schema": null
        },
        {
          "type": "int",
          "usage": 0.0,
          "schema": {
            "min_value": 0,
            "max_value": 140,
            "avr_value": 103.76
          }
        }
      ],
      "thumbnail_width": [
        {
          "type": "null",
          "usage": 1.0,
          "schema": null
        },
        {
          "type": "int",
          "usage": 0.0,
          "schema": {
            "min_value": 0,
            "max_value": 140,
            "avr_value": 129.04
          }
        }
      ],
      "approved": [
        {
          "type": "bool",
          "usage": "always",
          "schema": {
            "true": 0,
            "false": 5700
          }
        }
      ],
      "ignore_reports": [
        {
          "type": "bool",
          "usage": "always",
          "schema": {
            "true": 0,
            "false": 5700
          }
        }
      ],
      "removed": [
        {
          "type": "bool",
          "usage": "always",
          "schema": {
            "true": 0,
            "false": 5700
          }
        }
      ],
      "spam": [
        {
          "type": "bool",
          "usage": "always",
          "schema": {
            "true": 0,
            "false": 5700
          }
        }
      ],
      "author_cakeday": [
        {
          "type": "bool",
          "usage": "always",
          "schema": {
            "true": 297,
            "false": 0
          }
        }
      ],
      "post_hint": [
        {
          "type": "string",
          "usage": "always",
          "schema": {
            "min_length": 0,
            "max_length": 10,
            "avr_length": 4.36,
            "values": [
              {
                "value": "link",
                "usage": 0.89
              },
              {
                "value": "rich:video",
                "usage": 0.05
              },
              {
                "value": "image",
                "usage": 0.06
              }
            ]
          }
        }
      ],
      "preview": [
        {
          "type": "object",
          "usage": "always",
          "schema": {
            "enabled": [
              {
                "type": "bool",
                "usage": "always",
                "schema": {
                  "true": 9,
                  "false": 148
                }
              }
            ],
            "images": [
              {
                "type": "array",
                "usage": "always",
                "schema": {
                  "min_length": 0,
                  "max_length": 1,
                  "avr_length": 1.0,
                  "schema": [
                    {
                      "type": "object",
                      "usage": "always",
                      "schema": {
                        "id": [
                          {
                            "type": "string",
                            "usage": "always",
                            "schema": {
                              "min_length": 0,
                              "max_length": 43,
                              "avr_length": 43.0
                            }
                          }
                        ],
                        "resolutions": [
                          {
                            "type": "array",
                            "usage": "always",
                            "schema": {
                              "min_length": 0,
                              "max_length": 6,
                              "avr_length": 2.59,
                              "schema": [
                                {
                                  "type": "object",
                                  "usage": "always",
                                  "schema": {
                                    "height": [
                                      {
                                        "type": "int",
                                        "usage": "always",
                                        "schema": {
                                          "min_value": 0,
                                          "max_value": 1662,
                                          "avr_value": 226.33
                                        }
                                      }
                                    ],
                                    "url": [
                                      {
                                        "type": "string",
                                        "usage": "always",
                                        "schema": {
                                          "min_length": 0,
                                          "max_length": 177,
                                          "avr_length": 166.09
                                        }
                                      }
                                    ],
                                    "width": [
                                      {
                                        "type": "int",
                                        "usage": "always",
                                        "schema": {
                                          "min_value": 0,
                                          "max_value": 1080,
                                          "avr_value": 296.16
                                        }
                                      }
                                    ]
                                  }
                                }
                              ]
                            }
                          }
                        ],
                        "source": [
                          {
                            "type": "object",
                            "usage": "always",
                            "schema": {
                              "height": [
                                {
                                  "type": "int",
                                  "usage": "always",
                                  "schema": {
                                    "min_value": 0,
                                    "max_value": 2955,
                                    "avr_value": 386.47
                                  }
                                }
                              ],
                              "url": [
                                {
                                  "type": "string",
                                  "usage": "always",
                                  "schema": {
                                    "min_length": 0,
                                    "max_length": 119,
                                    "avr_length": 108.14
                                  }
                                }
                              ],
                              "width": [
                                {
                                  "type": "int",
                                  "usage": "always",
                                  "schema": {
                                    "min_value": 0,
                                    "max_value": 2000,
                                    "avr_value": 472.94
                                  }
                                }
                              ]
                            }
                          }
                        ],
                        "variants": [
                          {
                            "type": "object",
                            "usage": "always",
                            "schema": {
                              "nsfw": [
                                {
                                  "type": "object",
                                  "usage": "always",
                                  "schema": {
                                    "resolutions": [
                                      {
                                        "type": "array",
                                        "usage": "always",
                                        "schema": {
                                          "min_length": 0,
                                          "max_length": 3,
                                          "avr_length": 2.0,
                                          "schema": [
                                            {
                                              "type": "object",
                                              "usage": "always",
                                              "schema": {
                                                "height": [
                                                  {
                                                    "type": "int",
                                                    "usage": "always",
                                                    "schema": {
                                                      "min_value": 0,
                                                      "max_value": 240,
                                                      "avr_value": 144.64
                                                    }
                                                  }
                                                ],
                                                "url": [
                                                  {
                                                    "type": "string",
                                                    "usage": "always",
                                                    "schema": {
                                                      "min_length": 0,
                                                      "max_length": 200,
                                                      "avr_length": 200.0
                                                    }
                                                  }
                                                ],
                                                "width": [
                                                  {
                                                    "type": "int",
                                                    "usage": "always",
                                                    "schema": {
                                                      "min_value": 0,
                                                      "max_value": 320,
                                                      "avr_value": 176.86
                                                    }
                                                  }
                                                ]
                                              }
                                            }
                                          ]
                                        }
                                      }
                                    ],
                                    "source": [
                                      {
                                        "type": "object",
                                        "usage": "always",
                                        "schema": {
                                          "height": [
                                            {
                                              "type": "int",
                                              "usage": "always",
                                              "schema": {
                                                "min_value": 0,
                                                "max_value": 360,
                                                "avr_value": 259.14
                                              }
                                            }
                                          ],
                                          "url": [
                                            {
                                              "type": "string",
                                              "usage": "always",
                                              "schema": {
                                                "min_length": 0,
                                                "max_length": 142,
                                                "avr_length": 142.0
                                              }
                                            }
                                          ],
                                          "width": [
                                            {
                                              "type": "int",
                                              "usage": "always",
                                              "schema": {
                                                "min_value": 0,
                                                "max_value": 480,
                                                "avr_value": 305.71
                                              }
                                            }
                                          ]
                                        }
                                      }
                                    ]
                                  }
                                }
                              ],
                              "obfuscated": [
                                {
                                  "type": "object",
                                  "usage": "always",
                                  "schema": {
                                    "resolutions": [
                                      {
                                        "type": "array",
                                        "usage": "always",
                                        "schema": {
                                          "min_length": 0,
                                          "max_length": 3,
                                          "avr_length": 2.0,
                                          "schema": [
                                            {
                                              "type": "object",
                                              "usage": "always",
                                              "schema": {
                                                "height": [
                                                  {
                                                    "type": "int",
                                                    "usage": "always",
                                                    "schema": {
                                                      "min_value": 0,
                                                      "max_value": 240,
                                                      "avr_value": 144.64
                                                    }
                                                  }
                                                ],
                                                "url": [
                                                  {
                                                    "type": "string",
                                                    "usage": "always",
                                                    "schema": {
                                                      "min_length": 0,
                                                      "max_length": 200,
                                                      "avr_length": 200.0
                                                    }
                                                  }
                                                ],
                                                "width": [
                                                  {
                                                    "type": "int",
                                                    "usage": "always",
                                                    "schema": {
                                                      "min_value": 0,
                                                      "max_value": 320,
                                                      "avr_value": 176.86
                                                    }
                                                  }
                                                ]
                                              }
                                            }
                                          ]
                                        }
                                      }
                                    ],
                                    "source": [
                                      {
                                        "type": "object",
                                        "usage": "always",
                                        "schema": {
                                          "height": [
                                            {
                                              "type": "int",
                                              "usage": "always",
                                              "schema": {
                                                "min_value": 0,
                                                "max_value": 360,
                                                "avr_value": 259.14
                                              }
                                            }
                                          ],
                                          "url": [
                                            {
                                              "type": "string",
                                              "usage": "always",
                                              "schema": {
                                                "min_length": 0,
                                                "max_length": 142,
                                                "avr_length": 142.0
                                              }
                                            }
                                          ],
                                          "width": [
                                            {
                                              "type": "int",
                                              "usage": "always",
                                              "schema": {
                                                "min_value": 0,
                                                "max_value": 480,
                                                "avr_value": 305.71
                                              }
                                            }
                                          ]
                                        }
                                      }
                                    ]
                                  }
                                }
                              ],
                              "gif": [
                                {
                                  "type": "object",
                                  "usage": "always",
                                  "schema": {
                                    "resolutions": [
                                      {
                                        "type": "array",
                                        "usage": "always",
                                        "schema": {
                                          "min_length": 0,
                                          "max_length": 1,
                                          "avr_length": 1.0,
                                          "schema": [
                                            {
                                              "type": "object",
                                              "usage": "always",
                                              "schema": {
                                                "height": [
                                                  {
                                                    "type": "int",
                                                    "usage": "always",
                                                    "schema": {
                                                      "min_value": 0,
                                                      "max_value": 92,
                                                      "avr_value": 92.0
                                                    }
                                                  }
                                                ],
                                                "url": [
                                                  {
                                                    "type": "string",
                                                    "usage": "always",
                                                    "schema": {
                                                      "min_length": 0,
                                                      "max_length": 166,
                                                      "avr_length": 166.0
                                                    }
                                                  }
                                                ],
                                                "width": [
                                                  {
                                                    "type": "int",
                                                    "usage": "always",
                                                    "schema": {
                                                      "min_value": 0,
                                                      "max_value": 108,
                                                      "avr_value": 108.0
                                                    }
                                                  }
                                                ]
                                              }
                                            }
                                          ]
                                        }
                                      }
                                    ],
                                    "source": [
                                      {
                                        "type": "object",
                                        "usage": "always",
                                        "schema": {
                                          "height": [
                                            {
                                              "type": "int",
                                              "usage": "always",
                                              "schema": {
                                                "min_value": 0,
                                                "max_value": 120,
                                                "avr_value": 120.0
                                              }
                                            }
                                          ],
                                          "url": [
                                            {
                                              "type": "string",
                                              "usage": "always",
                                              "schema": {
                                                "min_length": 0,
                                                "max_length": 108,
                                                "avr_length": 108.0
                                              }
                                            }
                                          ],
                                          "width": [
                                            {
                                              "type": "int",
                                              "usage": "always",
                                              "schema": {
                                                "min_value": 0,
                                                "max_value": 140,
                                                "avr_value": 140.0
                                              }
                                            }
                                          ]
                                        }
                                      }
                                    ]
                                  }
                                }
                              ],
                              "mp4": [
                                {
                                  "type": "object",
                                  "usage": "always",
                                  "schema": {
                                    "resolutions": [
                                      {
                                        "type": "array",
                                        "usage": "always",
                                        "schema": {
                                          "min_length": 0,
                                          "max_length": 1,
                                          "avr_length": 1.0,
                                          "schema": [
                                            {
                                              "type": "object",
                                              "usage": "always",
                                              "schema": {
                                                "height": [
                                                  {
                                                    "type": "int",
                                                    "usage": "always",
                                                    "schema": {
                                                      "min_value": 0,
                                                      "max_value": 92,
                                                      "avr_value": 92.0
                                                    }
                                                  }
                                                ],
                                                "url": [
                                                  {
                                                    "type": "string",
                                                    "usage": "always",
                                                    "schema": {
                                                      "min_length": 0,
                                                      "max_length": 202,
                                                      "avr_length": 202.0
                                                    }
                                                  }
                                                ],
                                                "width": [
                                                  {
                                                    "type": "int",
                                                    "usage": "always",
                                                    "schema": {
                                                      "min_value": 0,
                                                      "max_value": 108,
                                                      "avr_value": 108.0
                                                    }
                                                  }
                                                ]
                                              }
                                            }
                                          ]
                                        }
                                      }
                                    ],
                                    "source": [
                                      {
                                        "type": "object",
                                        "usage": "always",
                                        "schema": {
                                          "height": [
                                            {
                                              "type": "int",
                                              "usage": "always",
                                              "schema": {
                                                "min_value": 0,
                                                "max_value": 120,
                                                "avr_value": 120.0
                                              }
                                            }
                                          ],
                                          "url": [
                                            {
                                              "type": "string",
                                              "usage": "always",
                                              "schema": {
                                                "min_length": 0,
                                                "max_length": 144,
                                                "avr_length": 144.0
                                              }
                                            }
                                          ],
                                          "width": [
                                            {
                                              "type": "int",
                                              "usage": "always",
                                              "schema": {
                                                "min_value": 0,
                                                "max_value": 140,
                                                "avr_value": 140.0
                                              }
                                            }
                                          ]
                                        }
                                      }
                                    ]
                                  }
                                }
                              ]
                            }
                          }
                        ]
                      }
                    }
                  ]
                }
              }
            ]
          }
        }
      ],
      "adserver_click_url": [
        {
          "type": "null",
          "usage": "always",
          "schema": null
        }
      ],
      "adserver_imp_pixel": [
        {
          "type": "null",
          "usage": "always",
          "schema": null
        }
      ],
      "author_id": [
        {
          "type": "string",
          "usage": "always",
          "schema": {
            "min_length": 0,
            "max_length": 8,
            "avr_length": 7.42,
            "values": [
              {
                "value": "t2_1w72",
                "usage": 0.08
              },
              {
                "value": "t2_1s9v",
                "usage": 0.25
              },
              {
                "value": "t2_1ed7b",
                "usage": 0.42
              },
              {
                "value": "t2_1wh0",
                "usage": 0.25
              }
            ]
          }
        }
      ],
      "domain_override": [
        {
          "type": "null",
          "usage": "always",
          "schema": null
        }
      ],
      "embed_type": [
        {
          "type": "null",
          "usage": "always",
          "schema": null
        }
      ],
      "embed_url": [
        {
          "type": "null",
          "usage": "always",
          "schema": null
        }
      ],
      "events": [
        {
          "type": "array",
          "usage": "always",
          "schema": {
            "min_length": 0,
            "max_length": 0,
            "avr_length": 0.0,
            "schema": []
          }
        }
      ],
      "eventsOnRender": [
        {
          "type": "array",
          "usage": "always",
          "schema": {
            "min_length": 0,
            "max_length": 0,
            "avr_length": 0.0,
            "schema": []
          }
        }
      ],
      "href_url": [
        {
          "type": "string",
          "usage": "always",
          "schema": {
            "min_length": 0,
            "max_length": 174,
            "avr_length": 94.42
          }
        }
      ],
      "is_blank": [
        {
          "type": "bool",
          "usage": "always",
          "schema": {
            "true": 0,
            "false": 12
          }
        }
      ],
      "mobile_ad_url": [
        {
          "type": "string",
          "usage": "always",
          "schema": {
            "min_length": 0,
            "max_length": 0,
            "avr_length": 0.0,
            "values": [
              {
                "value": "",
                "usage": "always"
              }
            ]
          }
        }
      ],
      "original_link": [
        {
          "type": "null",
          "usage": "always",
          "schema": null
        }
      ],
      "outbound_link": [
        {
          "type": "object",
          "usage": "always",
          "schema": {}
        }
      ],
      "priority_id": [
        {
          "type": "null",
          "usage": "always",
          "schema": null
        }
      ],
      "promoted": [
        {
          "type": "bool",
          "usage": "always",
          "schema": {
            "true": 12,
            "false": 0
          }
        }
      ],
      "promoted_by": [
        {
          "type": "int",
          "usage": 0.92,
          "schema": {
            "min_value": 0,
            "max_value": 88740,
            "avr_value": 88512.18
          }
        },
        {
          "type": "null",
          "usage": 0.08,
          "schema": null
        }
      ],
      "promoted_display_name": [
        {
          "type": "null",
          "usage": "always",
          "schema": null
        }
      ],
      "promoted_url": [
        {
          "type": "null",
          "usage": "always",
          "schema": null
        }
      ],
      "third_party_trackers": [
        {
          "type": "array",
          "usage": "always",
          "schema": {
            "min_length": 0,
            "max_length": 0,
            "avr_length": 0.0,
            "schema": []
          }
        }
      ],
      "third_party_tracking": [
        {
          "type": "null",
          "usage": "always",
          "schema": null
        }
      ],
      "third_party_tracking_2": [
        {
          "type": "null",
          "usage": "always",
          "schema": null
        }
      ],
      "link_flair_background_color": [
        {
          "type": "string",
          "usage": "always",
          "schema": {
            "min_length": 0,
            "max_length": 0,
            "avr_length": 0.0,
            "values": [
              {
                "value": "",
                "usage": "always"
              }
            ]
          }
        }
      ]
    }
  }
]